demos/__init__.py
demos/listbox.py
demos/main.py
demos/vbox.py
stewie/__init__.py
stewie/__main__.py
stewie/__version__.py
stewie/application.py
stewie/canvas.py
stewie/events.py
stewie/keyboard.py
stewie/main.py
stewie/utils.py
stewie/validate.py
stewie/widgettree.py
stewie/containers/__init__.py
stewie/containers/container.py
stewie/containers/frame.py
stewie/containers/hbox.py
stewie/containers/listbox.py
stewie/containers/vbox.py
stewie/styles/__init__.py
stewie/styles/boxattribute.py
stewie/styles/boxstyle.py
stewie/styles/colorattribute.py
stewie/styles/sizeattribute.py
stewie/styles/style.py
stewie/widgets/__init__.py
stewie/widgets/button.py
stewie/widgets/checkbox.py
stewie/widgets/label.py
stewie/widgets/numberbox.py
stewie/widgets/optionbox.py
stewie/widgets/passwordbox.py
stewie/widgets/progressbar.py
stewie/widgets/textbox.py
stewie/widgets/utils.py
stewie/widgets/widget.py
stewie-0.1.3rc0.dist-info/LICENSE
stewie-0.1.3rc0.dist-info/METADATA
stewie-0.1.3rc0.dist-info/WHEEL
stewie-0.1.3rc0.dist-info/top_level.txt
stewie-0.1.3rc0.dist-info/RECORD
