Metadata-Version: 2.1
Name: stewie
Version: 0.1.3rc0
Summary: Simple Terminal Widget Engine
Home-page: https://github.com/henrykrumb/stewie
Author: Henry Krumb
Author-email: henry.krumb@computerwerk.org
License: UNKNOWN
Platform: UNKNOWN
